nullfinder/__init__.py
nullfinder/__main__.py
nullfinder/utils.py
nullfinder/assets/icon.png
nullfinder/core/__init__.py
nullfinder/core/data_processing.py
nullfinder/ui/__init__.py
nullfinder/ui/about_dialog.py
nullfinder/ui/main_window.py
nullfinder/ui/components/__init__.py
nullfinder/ui/components/plot_overview.py
nullfinder-0.0.10.dist-info/licenses/LICENSE
nullfinder-0.0.10.dist-info/METADATA
nullfinder-0.0.10.dist-info/WHEEL
nullfinder-0.0.10.dist-info/entry_points.txt
nullfinder-0.0.10.dist-info/top_level.txt
nullfinder-0.0.10.dist-info/RECORD
